Flask_HAL_BBVA-1.0.5.dist-info/DESCRIPTION.rst
Flask_HAL_BBVA-1.0.5.dist-info/METADATA
Flask_HAL_BBVA-1.0.5.dist-info/RECORD
Flask_HAL_BBVA-1.0.5.dist-info/WHEEL
Flask_HAL_BBVA-1.0.5.dist-info/metadata.json
Flask_HAL_BBVA-1.0.5.dist-info/top_level.txt
flask_hal/__init__.py
flask_hal/document.py
flask_hal/link.py
